ingaia/__init__.py
ingaia/__main__.py
ingaia/api/__init__.py
ingaia/api/exceptions.py
ingaia/api/openapi_util.py
ingaia/authentication/__init__.py
ingaia/authentication/authutil.py
ingaia/authentication/config.py
ingaia/authentication/decode.py
ingaia/authentication/jwt-key.pub
ingaia/commons/__init__.py
ingaia/commons/exceptions.py
ingaia/commons/request_util.py
ingaia/constants/__init__.py
ingaia/constants/cons.py
ingaia/gcloud/__init__.py
ingaia/gcloud/bigquery.py
ingaia/gcloud/datastore.py
ingaia/gcloud/exceptions.py
ingaia/gcloud/firestore.py
ingaia/gcloud/project.py
ingaia/gcloud/queue.py
ingaia/gcloud/scheduler.py
ingaia/gcloud/schemas.py
ingaia/gcloud/storage.py
ingaia/request_logger/__init__.py
ingaia/request_logger/config.py
ingaia/request_logger/decode.py
ingaia/request_logger/exceptions.py
ingaia/request_logger/helper.py
ingaia/request_logger/request_logger.py
ingaia_libs-0.0.52.dist-info/DESCRIPTION.rst
ingaia_libs-0.0.52.dist-info/METADATA
ingaia_libs-0.0.52.dist-info/RECORD
ingaia_libs-0.0.52.dist-info/WHEEL
ingaia_libs-0.0.52.dist-info/entry_points.txt
ingaia_libs-0.0.52.dist-info/metadata.json
ingaia_libs-0.0.52.dist-info/top_level.txt
