Metadata-Version: 2.0
Name: ingaia-libs
Version: 0.0.52
Summary: inGaia Python Utility Library
Home-page: http://gitlab.ingaia.com.br/operacoes/libs/ingaia-libs
Author: inGaia Operations
Author-email: suporte.operacoes@i-value.com.br
License: MIT
Platform: UNKNOWN
Classifier: License :: OSI Approved :: MIT License
Classifier: Programming Language :: Python :: 3
Classifier: Programming Language :: Python :: 3.7
Classifier: Operating System :: OS Independent
Requires-Dist: google-cloud-firestore
Requires-Dist: google-cloud-datastore
Requires-Dist: google-cloud-tasks
Requires-Dist: google-cloud-storage
Requires-Dist: google-cloud-bigquery
Requires-Dist: flask
Requires-Dist: google-cloud-scheduler
Requires-Dist: werkzeug
Requires-Dist: decorator
Requires-Dist: requests
Requires-Dist: pyjwt
Requires-Dist: six
Requires-Dist: cryptography
Requires-Dist: PyYAML
Requires-Dist: m2r
